envirohat/__init__.py
envirohat-1.1.dist-info/LICENSE
envirohat-1.1.dist-info/METADATA
envirohat-1.1.dist-info/WHEEL
envirohat-1.1.dist-info/top_level.txt
envirohat-1.1.dist-info/RECORD
