Metadata-Version: 2.1
Name: envirohat
Version: 1.1
Summary: Enviro+ sensor in one place
Author-email: Jakub Bucko <bucko.jakub@proton.me>
Project-URL: Homepage, https://github.com/achjaj/envirohat
Project-URL: Bug Tracker, https://github.com/achjaj/envirohat/issues
Classifier: Programming Language :: Python :: 3
Classifier: License :: OSI Approved :: MIT License
Classifier: Operating System :: OS Independent
Requires-Python: >=3.6
License-File: LICENSE
Requires-Dist: enviroplus >=0.0.6
Requires-Dist: numpy >=1.19.5
Requires-Dist: smbus2 >=0.4.3
